gregorian/__init__.py
gregorian/calendar.py
gregorian/internals.py
gregorian/utils.py
gregorian-0.0.9.dist-info/LICENCE
gregorian-0.0.9.dist-info/METADATA
gregorian-0.0.9.dist-info/WHEEL
gregorian-0.0.9.dist-info/top_level.txt
gregorian-0.0.9.dist-info/RECORD
