Metadata-Version: 2.1
Name: gregorian
Version: 0.0.9
Summary: A calendar wrapper
Home-page: https://github.com/dschenck/gregorian
Author: david.schenck@outlook.com
Author-email: david.schenck@outlook.com
License: UNKNOWN
Platform: UNKNOWN
Classifier: Programming Language :: Python :: 3
Classifier: License :: OSI Approved :: MIT License
Classifier: Operating System :: OS Independent
Requires-Dist: python-dateutil
Requires-Dist: sortedcontainers
